cdpkit/__init__.py
cdpkit/logger.py
cdpkit/connection/__init__.py
cdpkit/connection/session.py
cdpkit/connection/manager/__init__.py
cdpkit/connection/manager/commands.py
cdpkit/connection/manager/events.py
cdpkit/exception/__init__.py
cdpkit/exception/base.py
cdpkit/exception/browser.py
cdpkit/exception/connection.py
cdpkit/exception/generate.py
cdpkit/protocol/__init__.py
cdpkit/protocol/_types.py
cdpkit/protocol/base.py
cdpkit/protocol/Accessibility/__init__.py
cdpkit/protocol/Accessibility/events.py
cdpkit/protocol/Accessibility/methods.py
cdpkit/protocol/Accessibility/types.py
cdpkit/protocol/Animation/__init__.py
cdpkit/protocol/Animation/events.py
cdpkit/protocol/Animation/methods.py
cdpkit/protocol/Animation/types.py
cdpkit/protocol/Audits/__init__.py
cdpkit/protocol/Audits/events.py
cdpkit/protocol/Audits/methods.py
cdpkit/protocol/Audits/types.py
cdpkit/protocol/Autofill/__init__.py
cdpkit/protocol/Autofill/events.py
cdpkit/protocol/Autofill/methods.py
cdpkit/protocol/Autofill/types.py
cdpkit/protocol/BackgroundService/__init__.py
cdpkit/protocol/BackgroundService/events.py
cdpkit/protocol/BackgroundService/methods.py
cdpkit/protocol/BackgroundService/types.py
cdpkit/protocol/BluetoothEmulation/__init__.py
cdpkit/protocol/BluetoothEmulation/events.py
cdpkit/protocol/BluetoothEmulation/methods.py
cdpkit/protocol/BluetoothEmulation/types.py
cdpkit/protocol/Browser/__init__.py
cdpkit/protocol/Browser/events.py
cdpkit/protocol/Browser/methods.py
cdpkit/protocol/Browser/types.py
cdpkit/protocol/CSS/__init__.py
cdpkit/protocol/CSS/events.py
cdpkit/protocol/CSS/methods.py
cdpkit/protocol/CSS/types.py
cdpkit/protocol/CacheStorage/__init__.py
cdpkit/protocol/CacheStorage/events.py
cdpkit/protocol/CacheStorage/methods.py
cdpkit/protocol/CacheStorage/types.py
cdpkit/protocol/Cast/__init__.py
cdpkit/protocol/Cast/events.py
cdpkit/protocol/Cast/methods.py
cdpkit/protocol/Cast/types.py
cdpkit/protocol/Console/__init__.py
cdpkit/protocol/Console/events.py
cdpkits-1.2.17.dist-info/licenses/LICENSE
cdpkits-1.2.17.dist-info/METADATA
cdpkits-1.2.17.dist-info/WHEEL
cdpkits-1.2.17.dist-info/top_level.txt
cdpkits-1.2.17.dist-info/RECORD
