Metadata-Version: 2.4
Name: cdpkits
Version: 1.2.17
Summary: Chrome DevTools Protocol Toolkit in Python
Project-URL: Homepage, https://github.com/yie1d/cdpkit
Classifier: Development Status :: 5 - Production/Stable
Classifier: Intended Audience :: Developers
Classifier: Operating System :: POSIX :: Linux
Classifier: Operating System :: MacOS :: MacOS X
Classifier: Operating System :: Microsoft :: Windows
Classifier: Programming Language :: Python
Classifier: Programming Language :: Python :: 3
Classifier: Programming Language :: Python :: 3.11
Classifier: Programming Language :: Python :: 3.12
Classifier: Programming Language :: Python :: 3.13
Classifier: Programming Language :: Python :: 3.14
Classifier: Topic :: Software Development :: Libraries
Classifier: Topic :: Software Development :: Libraries :: Python Modules
Requires-Python: >=3.11
License-File: LICENSE
Requires-Dist: aiohttp>=3.11.18
Requires-Dist: loguru>=0.7.3
Requires-Dist: pydantic>=2.11.3
Requires-Dist: websockets>=15.0.1
Dynamic: license-file
